nscolors/__init__.py
nscolors/bg.py
nscolors/colors.py
nscolors/core.py
nscolors/cursor.py
nscolors/direct.py
nscolors/fg.py
nscolors/progress.py
nscolors/tables.py
nscolors/palettes/ansi16_bg_palette.json
nscolors/palettes/ansi16_fg_palette.json
nscolors/palettes/text_styles.json
nscolors/palettes/winapi_bg_palette.txt
nscolors/palettes/winapi_fg_palette.txt
nscolors-1.0.2.1.dist-info/licenses/LICENSE
nscolors-1.0.2.1.dist-info/METADATA
nscolors-1.0.2.1.dist-info/WHEEL
nscolors-1.0.2.1.dist-info/top_level.txt
nscolors-1.0.2.1.dist-info/RECORD
