Metadata-Version: 2.4
Name: nscolors
Version: 1.0.2.1
Summary: Lightweight cross-platform terminal coloring & utilities for Python
Author: NullSpecter404
License: MIT
Project-URL: Homepage, https://github.com/NullSpecter404/nscolors-project
Project-URL: Repository, https://github.com/NullSpecter404/nscolors-project
Project-URL: Issue Tracker, https://github.com/NullSpecter404/nscolors-project/issues
Keywords: terminal,color,ansi,theme,cli,text-style,printing,cross-platform
Classifier: Development Status :: 4 - Beta
Classifier: Intended Audience :: Developers
Classifier: License :: OSI Approved :: MIT License
Classifier: Operating System :: OS Independent
Classifier: Programming Language :: Python :: 3
Classifier: Programming Language :: Python :: 3.7
Classifier: Programming Language :: Python :: 3.8
Classifier: Programming Language :: Python :: 3.9
Classifier: Programming Language :: Python :: 3.10
Classifier: Programming Language :: Python :: 3.11
Classifier: Programming Language :: Python :: 3.12
Classifier: Topic :: Software Development :: Libraries :: Python Modules
Classifier: Topic :: Terminals
Classifier: Topic :: Utilities
License-File: LICENSE
Provides-Extra: dev
Requires-Dist: pytest>=6.0; extra == "dev"
Requires-Dist: black>=22.0; extra == "dev"
Requires-Dist: flake8>=4.0; extra == "dev"
Dynamic: license-file
